good_valueserp/__init__.py
good_valueserp/_api.py
good_valueserp/_models.py
good_valueserp/_s3.py
good_valueserp-0.2.1.dist-info/METADATA
good_valueserp-0.2.1.dist-info/WHEEL
good_valueserp-0.2.1.dist-info/RECORD
