Metadata-Version: 2.4
Name: good-valueserp
Version: 0.2.1
Summary: Add your description here
Author-email: Chris Goddard <chris@goodkiwi.llc>
Requires-Python: >=3.12
Requires-Dist: good-common
Requires-Dist: good-object-storage
Requires-Dist: jsonlines>=4.0.0
Requires-Dist: orjson>=3.10.7
Requires-Dist: parse>=1.20.2
Requires-Dist: requests>=2.32.3
Requires-Dist: urllib3>=2.2.2
